[
  {
    "trend_arrow": "FLAT", 
    "display_time": "2016-07-26T06:40:02-04:00", 
    "system_time": "2016-07-26T14:40:32", 
    "direction": "Flat", 
    "dateString": "2016-07-26T06:40:02-04:00", 
    "date": 1469529602000, 
    "device": "openaps://cgm", 
    "sgv": 119, 
    "type": "sgv", 
    "glucose": 119
  }, 
  {
    "trend_arrow": "FLAT", 
    "display_time": "2016-07-26T06:35:02-04:00", 
    "system_time": "2016-07-26T14:35:32", 
    "direction": "Flat", 
    "dateString": "2016-07-26T06:35:02-04:00", 
    "date": 1469529302000, 
    "device": "openaps://cgm", 
    "sgv": 120, 
    "type": "sgv", 
    "glucose": 120
  }
]