[
  {
    "trend_arrow": "FLAT", 
    "display_time": "2016-07-28T19:14:58-04:00", 
    "system_time": "2016-07-29T03:15:29", 
    "direction": "Flat", 
    "dateString": "2016-07-28T19:14:58-04:00", 
    "date": 1469747698000, 
    "device": "openaps://cgm", 
    "sgv": 139, 
    "type": "sgv", 
    "glucose": 139
  }, 
  {
    "trend_arrow": "FLAT", 
    "display_time": "2016-07-28T19:09:52-04:00", 
    "system_time": "2016-07-29T03:10:23", 
    "direction": "Flat", 
    "dateString": "2016-07-28T19:09:52-04:00", 
    "date": 1469747392000, 
    "device": "openaps://cgm", 
    "sgv": 143, 
    "type": "sgv", 
    "glucose": 143
  }, 
  {
    "trend_arrow": "FLAT", 
    "display_time": "2016-07-28T19:29:55-04:00", 
    "system_time": "2016-07-29T03:30:25", 
    "direction": "Flat", 
    "dateString": "2016-07-28T19:29:55-04:00", 
    "date": 1469748595000, 
    "device": "openaps://cgm", 
    "sgv": 130, 
    "type": "sgv", 
    "glucose": 130
  }, 
  {
    "trend_arrow": "FLAT", 
    "display_time": "2016-07-28T19:24:53-04:00", 
    "system_time": "2016-07-29T03:25:24", 
    "direction": "Flat", 
    "dateString": "2016-07-28T19:24:53-04:00", 
    "date": 1469748293000, 
    "device": "openaps://cgm", 
    "sgv": 132, 
    "type": "sgv", 
    "glucose": 132
  }, 
  {
    "trend_arrow": "FLAT", 
    "display_time": "2016-07-28T19:49:54-04:00", 
    "system_time": "2016-07-29T03:50:25", 
    "direction": "Flat", 
    "dateString": "2016-07-28T19:49:54-04:00", 
    "date": 1469749794000, 
    "device": "openaps://cgm", 
    "sgv": 133, 
    "type": "sgv", 
    "glucose": 133
  }, 
  {
    "trend_arrow": "FLAT", 
    "display_time": "2016-07-28T19:44:53-04:00", 
    "system_time": "2016-07-29T03:45:23", 
    "direction": "Flat", 
    "dateString": "2016-07-28T19:44:53-04:00", 
    "date": 1469749493000, 
    "device": "openaps://cgm", 
    "sgv": 130, 
    "type": "sgv", 
    "glucose": 130
  }, 
  {
    "trend_arrow": "FLAT", 
    "display_time": "2016-07-28T19:54:57-04:00", 
    "system_time": "2016-07-29T03:55:27", 
    "direction": "Flat", 
    "dateString": "2016-07-28T19:54:57-04:00", 
    "date": 1469750097000, 
    "device": "openaps://cgm", 
    "sgv": 133, 
    "type": "sgv", 
    "glucose": 133
  }, 
  {
    "trend_arrow": "FLAT", 
    "display_time": "2016-07-28T19:49:54-04:00", 
    "system_time": "2016-07-29T03:50:25", 
    "direction": "Flat", 
    "dateString": "2016-07-28T19:49:54-04:00", 
    "date": 1469749794000, 
    "device": "openaps://cgm", 
    "sgv": 133, 
    "type": "sgv", 
    "glucose": 133
  }, 
  {
    "trend_arrow": "FLAT", 
    "display_time": "2016-07-28T20:04:58-04:00", 
    "system_time": "2016-07-29T04:05:28", 
    "direction": "Flat", 
    "dateString": "2016-07-28T20:04:58-04:00", 
    "date": 1469750698000, 
    "device": "openaps://cgm", 
    "sgv": 135, 
    "type": "sgv", 
    "glucose": 135
  }, 
  {
    "trend_arrow": "FLAT", 
    "display_time": "2016-07-28T19:59:51-04:00", 
    "system_time": "2016-07-29T04:00:22", 
    "direction": "Flat", 
    "dateString": "2016-07-28T19:59:51-04:00", 
    "date": 1469750391000, 
    "device": "openaps://cgm", 
    "sgv": 133, 
    "type": "sgv", 
    "glucose": 133
  }, 
  {
    "trend_arrow": "FLAT", 
    "display_time": "2016-07-28T20:20:10-04:00", 
    "system_time": "2016-07-29T04:20:40", 
    "direction": "Flat", 
    "dateString": "2016-07-28T20:20:10-04:00", 
    "date": 1469751610000, 
    "device": "openaps://cgm", 
    "sgv": 134, 
    "type": "sgv", 
    "glucose": 134
  }, 
  {
    "trend_arrow": "FLAT", 
    "display_time": "2016-07-28T20:14:53-04:00", 
    "system_time": "2016-07-29T04:15:23", 
    "direction": "Flat", 
    "dateString": "2016-07-28T20:14:53-04:00", 
    "date": 1469751293000, 
    "device": "openaps://cgm", 
    "sgv": 135, 
    "type": "sgv", 
    "glucose": 135
  }, 
  {
    "trend_arrow": "FLAT", 
    "display_time": "2016-07-28T20:30:14-04:00", 
    "system_time": "2016-07-29T04:30:44", 
    "direction": "Flat", 
    "dateString": "2016-07-28T20:30:14-04:00", 
    "date": 1469752214000, 
    "device": "openaps://cgm", 
    "sgv": 136, 
    "type": "sgv", 
    "glucose": 136
  }, 
  {
    "trend_arrow": "FLAT", 
    "display_time": "2016-07-28T20:25:04-04:00", 
    "system_time": "2016-07-29T04:25:34", 
    "direction": "Flat", 
    "dateString": "2016-07-28T20:25:04-04:00", 
    "date": 1469751904000, 
    "device": "openaps://cgm", 
    "sgv": 134, 
    "type": "sgv", 
    "glucose": 134
  }, 
  {
    "trend_arrow": "FLAT", 
    "display_time": "2016-07-28T20:39:59-04:00", 
    "system_time": "2016-07-29T04:40:30", 
    "direction": "Flat", 
    "dateString": "2016-07-28T20:39:59-04:00", 
    "date": 1469752799000, 
    "device": "openaps://cgm", 
    "sgv": 148, 
    "type": "sgv", 
    "glucose": 148
  }, 
  {
    "trend_arrow": "FLAT", 
    "display_time": "2016-07-28T20:34:54-04:00", 
    "system_time": "2016-07-29T04:35:24", 
    "direction": "Flat", 
    "dateString": "2016-07-28T20:34:54-04:00", 
    "date": 1469752494000, 
    "device": "openaps://cgm", 
    "sgv": 143, 
    "type": "sgv", 
    "glucose": 143
  }, 
  {
    "trend_arrow": "45_UP", 
    "display_time": "2016-07-28T20:49:56-04:00", 
    "system_time": "2016-07-29T04:50:26", 
    "direction": "FortyFiveUp", 
    "dateString": "2016-07-28T20:49:56-04:00", 
    "date": 1469753396000, 
    "device": "openaps://cgm", 
    "sgv": 173, 
    "type": "sgv", 
    "glucose": 173
  }, 
  {
    "trend_arrow": "45_UP", 
    "display_time": "2016-07-28T20:44:54-04:00", 
    "system_time": "2016-07-29T04:45:24", 
    "direction": "FortyFiveUp", 
    "dateString": "2016-07-28T20:44:54-04:00", 
    "date": 1469753094000, 
    "device": "openaps://cgm", 
    "sgv": 159, 
    "type": "sgv", 
    "glucose": 159
  }
]