[
  {
    "device": "openaps://raspberrypi", 
    "created_at": "2016-07-31T05:39:16.961Z", 
    "pump": {
      "battery": {
        "status": "normal", 
        "voltage": 1.25
      }, 
      "status": {
        "status": "normal", 
        "timestamp": "2016-07-31T05:38:31.000Z", 
        "bolusing": false, 
        "suspended": false
      }, 
      "reservoir": 137.425, 
      "clock": "2016-07-15T18:26:37-04:00"
    }, 
    "_id": "579d8f046738634d10834d9b", 
    "openaps": {
      "suggested": {
        "bg": 196, 
        "temp": "absolute", 
        "snoozeBG": 170, 
        "timestamp": "2016-07-31T05:38:53.000Z", 
        "reason": "Eventual BG 170>115 but Avg. Delta -6.00 < Exp. Delta -1.2, temp 0.75 ~ req 0.73U/hr", 
        "eventualBG": 170, 
        "mealAssist": "Off: Carbs: undefined Boluses: undefined ISF: 50, Target: 125 Deviation: -26 BGI: 0", 
        "tick": -6
      }, 
      "iob": {
        "netbasalinsulin": 0, 
        "timestamp": "2016-07-31T05:38:52.000Z", 
        "activity": 0, 
        "basaliob": 0, 
        "hightempinsulin": 0, 
        "bolussnooze": 0, 
        "iob": 0
      }, 
      "enacted": {
        "bg": 196, 
        "temp": "absolute", 
        "snoozeBG": 170, 
        "timestamp": "2016-07-31T05:38:56.000Z", 
        "missing": [
          "duration", 
          "rate"
        ], 
        "reason": "Eventual BG 170>115 but Avg. Delta -6.00 < Exp. Delta -1.2, temp 0.75 ~ req 0.73U/hr", 
        "eventualBG": 170, 
        "error": "missing required input fields", 
        "input": {
          "bg": 196, 
          "temp": "absolute", 
          "snoozeBG": 170, 
          "reason": "Eventual BG 170>115 but Avg. Delta -6.00 < Exp. Delta -1.2, temp 0.75 ~ req 0.73U/hr", 
          "eventualBG": 170, 
          "mealAssist": "Off: Carbs: undefined Boluses: undefined ISF: 50, Target: 125 Deviation: -26 BGI: 0", 
          "tick": -6
        }, 
        "mealAssist": "Off: Carbs: undefined Boluses: undefined ISF: 50, Target: 125 Deviation: -26 BGI: 0", 
        "tick": -6
      }
    }
  }
]