[
  {
    "trend_arrow": "FLAT", 
    "system_time": "2016-08-05T00:19:53", 
    "direction": "Flat", 
    "sgv": 68, 
    "display_time": "2016-08-04T16:19:22", 
    "date": 1470341962000.0, 
    "dateString": "2016-08-04T16:19:22", 
    "device": "openaps://cgm", 
    "type": "sgv", 
    "glucose": 68
  }, 
  {
    "trend_arrow": "FLAT", 
    "system_time": "2016-08-05T00:14:53", 
    "direction": "Flat", 
    "sgv": 71, 
    "display_time": "2016-08-04T16:14:23", 
    "date": 1470341663000.0, 
    "dateString": "2016-08-04T16:14:23", 
    "device": "openaps://cgm", 
    "type": "sgv", 
    "glucose": 71
  }, 
  {
    "trend_arrow": "FLAT", 
    "system_time": "2016-08-05T00:09:52", 
    "direction": "Flat", 
    "sgv": 72, 
    "display_time": "2016-08-04T16:09:21", 
    "date": 1470341361000.0, 
    "dateString": "2016-08-04T16:09:21", 
    "device": "openaps://cgm", 
    "type": "sgv", 
    "glucose": 72
  }, 
  {
    "trend_arrow": "FLAT", 
    "system_time": "2016-08-05T00:04:55", 
    "direction": "Flat", 
    "sgv": 74, 
    "display_time": "2016-08-04T16:04:25", 
    "date": 1470341065000.0, 
    "dateString": "2016-08-04T16:04:25", 
    "device": "openaps://cgm", 
    "type": "sgv", 
    "glucose": 74
  }, 
  {
    "trend_arrow": "FLAT", 
    "system_time": "2016-08-04T23:59:57", 
    "direction": "Flat", 
    "sgv": 75, 
    "display_time": "2016-08-04T15:59:27", 
    "date": 1470340767000.0, 
    "dateString": "2016-08-04T15:59:27", 
    "device": "openaps://cgm", 
    "type": "sgv", 
    "glucose": 75
  }, 
  {
    "trend_arrow": "FLAT", 
    "system_time": "2016-08-04T23:54:55", 
    "direction": "Flat", 
    "sgv": 76, 
    "display_time": "2016-08-04T15:54:24", 
    "date": 1470340464000.0, 
    "dateString": "2016-08-04T15:54:24", 
    "device": "openaps://cgm", 
    "type": "sgv", 
    "glucose": 76
  }, 
  {
    "trend_arrow": "FLAT", 
    "system_time": "2016-08-04T23:49:52", 
    "direction": "Flat", 
    "sgv": 79, 
    "display_time": "2016-08-04T15:49:22", 
    "date": 1470340162000.0, 
    "dateString": "2016-08-04T15:49:22", 
    "device": "openaps://cgm", 
    "type": "sgv", 
    "glucose": 79
  }, 
  {
    "trend_arrow": "FLAT", 
    "system_time": "2016-08-04T23:44:52", 
    "direction": "Flat", 
    "sgv": 81, 
    "display_time": "2016-08-04T15:44:21", 
    "date": 1470339861000.0, 
    "dateString": "2016-08-04T15:44:21", 
    "device": "openaps://cgm", 
    "type": "sgv", 
    "glucose": 81
  }, 
  {
    "trend_arrow": "FLAT", 
    "system_time": "2016-08-04T23:39:52", 
    "direction": "Flat", 
    "sgv": 85, 
    "display_time": "2016-08-04T15:39:22", 
    "date": 1470339562000.0, 
    "dateString": "2016-08-04T15:39:22", 
    "device": "openaps://cgm", 
    "type": "sgv", 
    "glucose": 85
  }, 
  {
    "trend_arrow": "FLAT", 
    "system_time": "2016-08-04T23:34:52", 
    "direction": "Flat", 
    "sgv": 89, 
    "display_time": "2016-08-04T15:34:21", 
    "date": 1470339261000.0, 
    "dateString": "2016-08-04T15:34:21", 
    "device": "openaps://cgm", 
    "type": "sgv", 
    "glucose": 89
  }, 
  {
    "trend_arrow": "45_DOWN", 
    "system_time": "2016-08-04T23:29:53", 
    "direction": "FortyFiveDown", 
    "sgv": 91, 
    "display_time": "2016-08-04T15:29:23", 
    "date": 1470338963000.0, 
    "dateString": "2016-08-04T15:29:23", 
    "device": "openaps://cgm", 
    "type": "sgv", 
    "glucose": 91
  }, 
  {
    "trend_arrow": "FLAT", 
    "system_time": "2016-08-04T23:24:50", 
    "direction": "Flat", 
    "sgv": 100, 
    "display_time": "2016-08-04T15:24:19", 
    "date": 1470338659000.0, 
    "dateString": "2016-08-04T15:24:19", 
    "device": "openaps://cgm", 
    "type": "sgv", 
    "glucose": 100
  }, 
  {
    "trend_arrow": "45_DOWN", 
    "system_time": "2016-08-04T23:19:50", 
    "direction": "FortyFiveDown", 
    "sgv": 98, 
    "display_time": "2016-08-04T15:19:19", 
    "date": 1470338359000.0, 
    "dateString": "2016-08-04T15:19:19", 
    "device": "openaps://cgm", 
    "type": "sgv", 
    "glucose": 98
  }, 
  {
    "trend_arrow": "FLAT", 
    "system_time": "2016-08-04T23:14:52", 
    "direction": "Flat", 
    "sgv": 107, 
    "display_time": "2016-08-04T15:14:22", 
    "date": 1470338062000.0, 
    "dateString": "2016-08-04T15:14:22", 
    "device": "openaps://cgm", 
    "type": "sgv", 
    "glucose": 107
  }, 
  {
    "trend_arrow": "FLAT", 
    "system_time": "2016-08-04T23:09:50", 
    "direction": "Flat", 
    "sgv": 110, 
    "display_time": "2016-08-04T15:09:20", 
    "date": 1470337760000.0, 
    "dateString": "2016-08-04T15:09:20", 
    "device": "openaps://cgm", 
    "type": "sgv", 
    "glucose": 110
  }, 
  {
    "trend_arrow": "FLAT", 
    "system_time": "2016-08-04T23:04:55", 
    "direction": "Flat", 
    "sgv": 112, 
    "display_time": "2016-08-04T15:04:24", 
    "date": 1470337464000.0, 
    "dateString": "2016-08-04T15:04:24", 
    "device": "openaps://cgm", 
    "type": "sgv", 
    "glucose": 112
  }, 
  {
    "trend_arrow": "FLAT", 
    "system_time": "2016-08-04T22:59:52", 
    "direction": "Flat", 
    "sgv": 116, 
    "display_time": "2016-08-04T14:59:21", 
    "date": 1470337161000.0, 
    "dateString": "2016-08-04T14:59:21", 
    "device": "openaps://cgm", 
    "type": "sgv", 
    "glucose": 116
  }, 
  {
    "trend_arrow": "FLAT", 
    "system_time": "2016-08-04T22:54:52", 
    "direction": "Flat", 
    "sgv": 118, 
    "display_time": "2016-08-04T14:54:22", 
    "date": 1470336862000.0, 
    "dateString": "2016-08-04T14:54:22", 
    "device": "openaps://cgm", 
    "type": "sgv", 
    "glucose": 118
  }, 
  {
    "trend_arrow": "FLAT", 
    "system_time": "2016-08-04T22:49:56", 
    "direction": "Flat", 
    "sgv": 121, 
    "display_time": "2016-08-04T14:49:25", 
    "date": 1470336565000.0, 
    "dateString": "2016-08-04T14:49:25", 
    "device": "openaps://cgm", 
    "type": "sgv", 
    "glucose": 121
  }, 
  {
    "trend_arrow": "FLAT", 
    "system_time": "2016-08-04T22:44:50", 
    "direction": "Flat", 
    "sgv": 124, 
    "display_time": "2016-08-04T14:44:20", 
    "date": 1470336260000.0, 
    "dateString": "2016-08-04T14:44:20", 
    "device": "openaps://cgm", 
    "type": "sgv", 
    "glucose": 124
  }, 
  {
    "trend_arrow": "FLAT", 
    "system_time": "2016-08-04T22:39:50", 
    "direction": "Flat", 
    "sgv": 128, 
    "display_time": "2016-08-04T14:39:20", 
    "date": 1470335960000.0, 
    "dateString": "2016-08-04T14:39:20", 
    "device": "openaps://cgm", 
    "type": "sgv", 
    "glucose": 128
  }, 
  {
    "trend_arrow": "FLAT", 
    "system_time": "2016-08-04T22:34:52", 
    "direction": "Flat", 
    "sgv": 131, 
    "display_time": "2016-08-04T14:34:21", 
    "date": 1470335661000.0, 
    "dateString": "2016-08-04T14:34:21", 
    "device": "openaps://cgm", 
    "type": "sgv", 
    "glucose": 131
  }, 
  {
    "trend_arrow": "FLAT", 
    "system_time": "2016-08-04T22:29:51", 
    "direction": "Flat", 
    "sgv": 134, 
    "display_time": "2016-08-04T14:29:21", 
    "date": 1470335361000.0, 
    "dateString": "2016-08-04T14:29:21", 
    "device": "openaps://cgm", 
    "type": "sgv", 
    "glucose": 134
  }, 
  {
    "trend_arrow": "FLAT", 
    "system_time": "2016-08-04T22:24:53", 
    "direction": "Flat", 
    "sgv": 135, 
    "display_time": "2016-08-04T14:24:22", 
    "date": 1470335062000.0, 
    "dateString": "2016-08-04T14:24:22", 
    "device": "openaps://cgm", 
    "type": "sgv", 
    "glucose": 135
  }
]