[
  {
    "trend_arrow": "FLAT", 
    "system_time": "2016-08-02T21:25:08", 
    "direction": "Flat", 
    "sgv": 122, 
    "display_time": "2016-08-02T13:24:37", 
    "date": 1470158677000.0, 
    "dateString": "2016-08-02T13:24:37", 
    "device": "openaps://cgm", 
    "type": "sgv", 
    "glucose": 122
  }, 
  {
    "trend_arrow": "FLAT", 
    "system_time": "2016-08-02T21:20:03", 
    "direction": "Flat", 
    "sgv": 121, 
    "display_time": "2016-08-02T13:19:32", 
    "date": 1470158372000.0, 
    "dateString": "2016-08-02T13:19:32", 
    "device": "openaps://cgm", 
    "type": "sgv", 
    "glucose": 121
  }, 
  {
    "trend_arrow": "FLAT", 
    "system_time": "2016-08-02T21:15:04", 
    "direction": "Flat", 
    "sgv": 118, 
    "display_time": "2016-08-02T13:14:33", 
    "date": 1470158073000.0, 
    "dateString": "2016-08-02T13:14:33", 
    "device": "openaps://cgm", 
    "type": "sgv", 
    "glucose": 118
  }, 
  {
    "trend_arrow": "FLAT", 
    "system_time": "2016-08-02T21:10:02", 
    "direction": "Flat", 
    "sgv": 115, 
    "display_time": "2016-08-02T13:09:31", 
    "date": 1470157771000.0, 
    "dateString": "2016-08-02T13:09:31", 
    "device": "openaps://cgm", 
    "type": "sgv", 
    "glucose": 115
  }, 
  {
    "trend_arrow": "FLAT", 
    "system_time": "2016-08-02T21:05:00", 
    "direction": "Flat", 
    "sgv": 116, 
    "display_time": "2016-08-02T13:04:29", 
    "date": 1470157469000.0, 
    "dateString": "2016-08-02T13:04:29", 
    "device": "openaps://cgm", 
    "type": "sgv", 
    "glucose": 116
  }, 
  {
    "trend_arrow": "FLAT", 
    "system_time": "2016-08-02T21:00:00", 
    "direction": "Flat", 
    "sgv": 119, 
    "display_time": "2016-08-02T12:59:29", 
    "date": 1470157169000.0, 
    "dateString": "2016-08-02T12:59:29", 
    "device": "openaps://cgm", 
    "type": "sgv", 
    "glucose": 119
  }, 
  {
    "trend_arrow": "FLAT", 
    "system_time": "2016-08-02T20:55:03", 
    "direction": "Flat", 
    "sgv": 123, 
    "display_time": "2016-08-02T12:54:33", 
    "date": 1470156873000.0, 
    "dateString": "2016-08-02T12:54:33", 
    "device": "openaps://cgm", 
    "type": "sgv", 
    "glucose": 123
  }, 
  {
    "trend_arrow": "FLAT", 
    "system_time": "2016-08-02T20:50:04", 
    "direction": "Flat", 
    "sgv": 126, 
    "display_time": "2016-08-02T12:49:34", 
    "date": 1470156574000.0, 
    "dateString": "2016-08-02T12:49:34", 
    "device": "openaps://cgm", 
    "type": "sgv", 
    "glucose": 126
  }, 
  {
    "trend_arrow": "FLAT", 
    "system_time": "2016-08-02T20:45:09", 
    "direction": "Flat", 
    "sgv": 125, 
    "display_time": "2016-08-02T12:44:38", 
    "date": 1470156278000.0, 
    "dateString": "2016-08-02T12:44:38", 
    "device": "openaps://cgm", 
    "type": "sgv", 
    "glucose": 125
  }, 
  {
    "trend_arrow": "FLAT", 
    "system_time": "2016-08-02T20:40:03", 
    "direction": "Flat", 
    "sgv": 127, 
    "display_time": "2016-08-02T12:39:33", 
    "date": 1470155973000.0, 
    "dateString": "2016-08-02T12:39:33", 
    "device": "openaps://cgm", 
    "type": "sgv", 
    "glucose": 127
  }, 
  {
    "trend_arrow": "FLAT", 
    "system_time": "2016-08-02T20:35:00", 
    "direction": "Flat", 
    "sgv": 128, 
    "display_time": "2016-08-02T12:34:30", 
    "date": 1470155670000.0, 
    "dateString": "2016-08-02T12:34:30", 
    "device": "openaps://cgm", 
    "type": "sgv", 
    "glucose": 128
  }, 
  {
    "trend_arrow": "FLAT", 
    "system_time": "2016-08-02T20:30:01", 
    "direction": "Flat", 
    "sgv": 129, 
    "display_time": "2016-08-02T12:29:31", 
    "date": 1470155371000.0, 
    "dateString": "2016-08-02T12:29:31", 
    "device": "openaps://cgm", 
    "type": "sgv", 
    "glucose": 129
  }, 
  {
    "trend_arrow": "FLAT", 
    "system_time": "2016-08-02T20:25:01", 
    "direction": "Flat", 
    "sgv": 127, 
    "display_time": "2016-08-02T12:24:30", 
    "date": 1470155070000.0, 
    "dateString": "2016-08-02T12:24:30", 
    "device": "openaps://cgm", 
    "type": "sgv", 
    "glucose": 127
  }, 
  {
    "trend_arrow": "FLAT", 
    "system_time": "2016-08-02T20:20:03", 
    "direction": "Flat", 
    "sgv": 124, 
    "display_time": "2016-08-02T12:19:33", 
    "date": 1470154773000.0, 
    "dateString": "2016-08-02T12:19:33", 
    "device": "openaps://cgm", 
    "type": "sgv", 
    "glucose": 124
  }, 
  {
    "trend_arrow": "45_UP", 
    "system_time": "2016-08-02T20:15:03", 
    "direction": "FortyFiveUp", 
    "sgv": 123, 
    "display_time": "2016-08-02T12:14:33", 
    "date": 1470154473000.0, 
    "dateString": "2016-08-02T12:14:33", 
    "device": "openaps://cgm", 
    "type": "sgv", 
    "glucose": 123
  }, 
  {
    "trend_arrow": "FLAT", 
    "system_time": "2016-08-02T20:10:02", 
    "direction": "Flat", 
    "sgv": 117, 
    "display_time": "2016-08-02T12:09:32", 
    "date": 1470154172000.0, 
    "dateString": "2016-08-02T12:09:32", 
    "device": "openaps://cgm", 
    "type": "sgv", 
    "glucose": 117
  }, 
  {
    "trend_arrow": "FLAT", 
    "system_time": "2016-08-02T20:05:01", 
    "direction": "Flat", 
    "sgv": 114, 
    "display_time": "2016-08-02T12:04:30", 
    "date": 1470153870000.0, 
    "dateString": "2016-08-02T12:04:30", 
    "device": "openaps://cgm", 
    "type": "sgv", 
    "glucose": 114
  }, 
  {
    "trend_arrow": "FLAT", 
    "system_time": "2016-08-02T20:00:07", 
    "direction": "Flat", 
    "sgv": 108, 
    "display_time": "2016-08-02T11:59:37", 
    "date": 1470153577000.0, 
    "dateString": "2016-08-02T11:59:37", 
    "device": "openaps://cgm", 
    "type": "sgv", 
    "glucose": 108
  }, 
  {
    "trend_arrow": "FLAT", 
    "system_time": "2016-08-02T19:55:03", 
    "direction": "Flat", 
    "sgv": 106, 
    "display_time": "2016-08-02T11:54:33", 
    "date": 1470153273000.0, 
    "dateString": "2016-08-02T11:54:33", 
    "device": "openaps://cgm", 
    "type": "sgv", 
    "glucose": 106
  }, 
  {
    "trend_arrow": "FLAT", 
    "system_time": "2016-08-02T19:50:07", 
    "direction": "Flat", 
    "sgv": 107, 
    "display_time": "2016-08-02T11:49:37", 
    "date": 1470152977000.0, 
    "dateString": "2016-08-02T11:49:37", 
    "device": "openaps://cgm", 
    "type": "sgv", 
    "glucose": 107
  }, 
  {
    "trend_arrow": "FLAT", 
    "system_time": "2016-08-02T19:45:08", 
    "direction": "Flat", 
    "sgv": 107, 
    "display_time": "2016-08-02T11:44:37", 
    "date": 1470152677000.0, 
    "dateString": "2016-08-02T11:44:37", 
    "device": "openaps://cgm", 
    "type": "sgv", 
    "glucose": 107
  }, 
  {
    "trend_arrow": "FLAT", 
    "system_time": "2016-08-02T19:40:06", 
    "direction": "Flat", 
    "sgv": 109, 
    "display_time": "2016-08-02T11:39:35", 
    "date": 1470152375000.0, 
    "dateString": "2016-08-02T11:39:35", 
    "device": "openaps://cgm", 
    "type": "sgv", 
    "glucose": 109
  }
]