[
  {
    "trend_arrow": "45_UP", 
    "system_time": "2016-07-20T20:10:16", 
    "direction": "FortyFiveUp", 
    "sgv": 121, 
    "display_time": "2016-07-20T12:09:45", 
    "date": 1469030985000.0, 
    "dateString": "2016-07-20T12:09:45", 
    "device": "openaps://cgm", 
    "type": "sgv", 
    "glucose": 121
  }, 
  {
    "trend_arrow": "45_UP", 
    "system_time": "2016-07-20T20:05:16", 
    "direction": "FortyFiveUp", 
    "sgv": 111, 
    "display_time": "2016-07-20T12:04:46", 
    "date": 1469030686000.0, 
    "dateString": "2016-07-20T12:04:46", 
    "device": "openaps://cgm", 
    "type": "sgv", 
    "glucose": 111
  }, 
  {
    "trend_arrow": "45_UP", 
    "system_time": "2016-07-20T20:00:17", 
    "direction": "FortyFiveUp", 
    "sgv": 101, 
    "display_time": "2016-07-20T11:59:46", 
    "date": 1469030386000.0, 
    "dateString": "2016-07-20T11:59:46", 
    "device": "openaps://cgm", 
    "type": "sgv", 
    "glucose": 101
  }, 
  {
    "trend_arrow": "45_UP", 
    "system_time": "2016-07-20T19:55:16", 
    "direction": "FortyFiveUp", 
    "sgv": 92, 
    "display_time": "2016-07-20T11:54:46", 
    "date": 1469030086000.0, 
    "dateString": "2016-07-20T11:54:46", 
    "device": "openaps://cgm", 
    "type": "sgv", 
    "glucose": 92
  }, 
  {
    "trend_arrow": "FLAT", 
    "system_time": "2016-07-20T19:50:16", 
    "direction": "Flat", 
    "sgv": 83, 
    "display_time": "2016-07-20T11:49:46", 
    "date": 1469029786000.0, 
    "dateString": "2016-07-20T11:49:46", 
    "device": "openaps://cgm", 
    "type": "sgv", 
    "glucose": 83
  }, 
  {
    "trend_arrow": "FLAT", 
    "system_time": "2016-07-20T19:45:16", 
    "direction": "Flat", 
    "sgv": 77, 
    "display_time": "2016-07-20T11:44:46", 
    "date": 1469029486000.0, 
    "dateString": "2016-07-20T11:44:46", 
    "device": "openaps://cgm", 
    "type": "sgv", 
    "glucose": 77
  }, 
  {
    "trend_arrow": "FLAT", 
    "system_time": "2016-07-20T19:40:17", 
    "direction": "Flat", 
    "sgv": 73, 
    "display_time": "2016-07-20T11:39:46", 
    "date": 1469029186000.0, 
    "dateString": "2016-07-20T11:39:46", 
    "device": "openaps://cgm", 
    "type": "sgv", 
    "glucose": 73
  }, 
  {
    "trend_arrow": "FLAT", 
    "system_time": "2016-07-20T19:35:16", 
    "direction": "Flat", 
    "sgv": 70, 
    "display_time": "2016-07-20T11:34:46", 
    "date": 1469028886000.0, 
    "dateString": "2016-07-20T11:34:46", 
    "device": "openaps://cgm", 
    "type": "sgv", 
    "glucose": 70
  }, 
  {
    "trend_arrow": "FLAT", 
    "system_time": "2016-07-20T19:30:17", 
    "direction": "Flat", 
    "sgv": 70, 
    "display_time": "2016-07-20T11:29:47", 
    "date": 1469028587000.0, 
    "dateString": "2016-07-20T11:29:47", 
    "device": "openaps://cgm", 
    "type": "sgv", 
    "glucose": 70
  }, 
  {
    "trend_arrow": "FLAT", 
    "system_time": "2016-07-20T19:25:16", 
    "direction": "Flat", 
    "sgv": 70, 
    "display_time": "2016-07-20T11:24:45", 
    "date": 1469028285000.0, 
    "dateString": "2016-07-20T11:24:45", 
    "device": "openaps://cgm", 
    "type": "sgv", 
    "glucose": 70
  }, 
  {
    "trend_arrow": "FLAT", 
    "system_time": "2016-07-20T19:20:21", 
    "direction": "Flat", 
    "sgv": 71, 
    "display_time": "2016-07-20T11:19:51", 
    "date": 1469027991000.0, 
    "dateString": "2016-07-20T11:19:51", 
    "device": "openaps://cgm", 
    "type": "sgv", 
    "glucose": 71
  }, 
  {
    "trend_arrow": "FLAT", 
    "system_time": "2016-07-20T19:15:16", 
    "direction": "Flat", 
    "sgv": 73, 
    "display_time": "2016-07-20T11:14:46", 
    "date": 1469027686000.0, 
    "dateString": "2016-07-20T11:14:46", 
    "device": "openaps://cgm", 
    "type": "sgv", 
    "glucose": 73
  }, 
  {
    "trend_arrow": "FLAT", 
    "system_time": "2016-07-20T19:10:17", 
    "direction": "Flat", 
    "sgv": 82, 
    "display_time": "2016-07-20T11:09:46", 
    "date": 1469027386000.0, 
    "dateString": "2016-07-20T11:09:46", 
    "device": "openaps://cgm", 
    "type": "sgv", 
    "glucose": 82
  }, 
  {
    "trend_arrow": "FLAT", 
    "system_time": "2016-07-20T18:55:22", 
    "direction": "Flat", 
    "sgv": 85, 
    "display_time": "2016-07-20T10:54:51", 
    "date": 1469026491000.0, 
    "dateString": "2016-07-20T10:54:51", 
    "device": "openaps://cgm", 
    "type": "sgv", 
    "glucose": 85
  }, 
  {
    "trend_arrow": "FLAT", 
    "system_time": "2016-07-20T18:50:17", 
    "direction": "Flat", 
    "sgv": 86, 
    "display_time": "2016-07-20T10:49:46", 
    "date": 1469026186000.0, 
    "dateString": "2016-07-20T10:49:46", 
    "device": "openaps://cgm", 
    "type": "sgv", 
    "glucose": 86
  }, 
  {
    "trend_arrow": "FLAT", 
    "system_time": "2016-07-20T18:45:18", 
    "direction": "Flat", 
    "sgv": 90, 
    "display_time": "2016-07-20T10:44:48", 
    "date": 1469025888000.0, 
    "dateString": "2016-07-20T10:44:48", 
    "device": "openaps://cgm", 
    "type": "sgv", 
    "glucose": 90
  }, 
  {
    "trend_arrow": "FLAT", 
    "system_time": "2016-07-20T18:40:18", 
    "direction": "Flat", 
    "sgv": 94, 
    "display_time": "2016-07-20T10:39:48", 
    "date": 1469025588000.0, 
    "dateString": "2016-07-20T10:39:48", 
    "device": "openaps://cgm", 
    "type": "sgv", 
    "glucose": 94
  }, 
  {
    "trend_arrow": "FLAT", 
    "system_time": "2016-07-20T18:35:20", 
    "direction": "Flat", 
    "sgv": 97, 
    "display_time": "2016-07-20T10:34:49", 
    "date": 1469025289000.0, 
    "dateString": "2016-07-20T10:34:49", 
    "device": "openaps://cgm", 
    "type": "sgv", 
    "glucose": 97
  }, 
  {
    "trend_arrow": "FLAT", 
    "system_time": "2016-07-20T18:30:17", 
    "direction": "Flat", 
    "sgv": 100, 
    "display_time": "2016-07-20T10:29:47", 
    "date": 1469024987000.0, 
    "dateString": "2016-07-20T10:29:47", 
    "device": "openaps://cgm", 
    "type": "sgv", 
    "glucose": 100
  }, 
  {
    "trend_arrow": "FLAT", 
    "system_time": "2016-07-20T18:25:17", 
    "direction": "Flat", 
    "sgv": 102, 
    "display_time": "2016-07-20T10:24:46", 
    "date": 1469024686000.0, 
    "dateString": "2016-07-20T10:24:46", 
    "device": "openaps://cgm", 
    "type": "sgv", 
    "glucose": 102
  }, 
  {
    "trend_arrow": "FLAT", 
    "system_time": "2016-07-20T18:20:16", 
    "direction": "Flat", 
    "sgv": 104, 
    "display_time": "2016-07-20T10:19:46", 
    "date": 1469024386000.0, 
    "dateString": "2016-07-20T10:19:46", 
    "device": "openaps://cgm", 
    "type": "sgv", 
    "glucose": 104
  }
]