[
  {
    "trend_arrow": "FLAT", 
    "system_time": "2016-08-02T23:05:02", 
    "direction": "Flat", 
    "sgv": 157, 
    "display_time": "2016-08-02T15:04:32", 
    "date": 1470164672000.0, 
    "dateString": "2016-08-02T15:04:32", 
    "device": "openaps://cgm", 
    "type": "sgv", 
    "glucose": 157
  }, 
  {
    "trend_arrow": "FLAT", 
    "system_time": "2016-08-02T23:00:01", 
    "direction": "Flat", 
    "sgv": 152, 
    "display_time": "2016-08-02T14:59:31", 
    "date": 1470164371000.0, 
    "dateString": "2016-08-02T14:59:31", 
    "device": "openaps://cgm", 
    "type": "sgv", 
    "glucose": 152
  }, 
  {
    "trend_arrow": "FLAT", 
    "system_time": "2016-08-02T22:55:00", 
    "direction": "Flat", 
    "sgv": 148, 
    "display_time": "2016-08-02T14:54:30", 
    "date": 1470164070000.0, 
    "dateString": "2016-08-02T14:54:30", 
    "device": "openaps://cgm", 
    "type": "sgv", 
    "glucose": 148
  }, 
  {
    "trend_arrow": "FLAT", 
    "system_time": "2016-08-02T22:50:02", 
    "direction": "Flat", 
    "sgv": 144, 
    "display_time": "2016-08-02T14:49:31", 
    "date": 1470163771000.0, 
    "dateString": "2016-08-02T14:49:31", 
    "device": "openaps://cgm", 
    "type": "sgv", 
    "glucose": 144
  }, 
  {
    "trend_arrow": "FLAT", 
    "system_time": "2016-08-02T22:45:01", 
    "direction": "Flat", 
    "sgv": 142, 
    "display_time": "2016-08-02T14:44:31", 
    "date": 1470163471000.0, 
    "dateString": "2016-08-02T14:44:31", 
    "device": "openaps://cgm", 
    "type": "sgv", 
    "glucose": 142
  }, 
  {
    "trend_arrow": "FLAT", 
    "system_time": "2016-08-02T22:39:59", 
    "direction": "Flat", 
    "sgv": 140, 
    "display_time": "2016-08-02T14:39:29", 
    "date": 1470163169000.0, 
    "dateString": "2016-08-02T14:39:29", 
    "device": "openaps://cgm", 
    "type": "sgv", 
    "glucose": 140
  }, 
  {
    "trend_arrow": "FLAT", 
    "system_time": "2016-08-02T22:34:59", 
    "direction": "Flat", 
    "sgv": 139, 
    "display_time": "2016-08-02T14:34:29", 
    "date": 1470162869000.0, 
    "dateString": "2016-08-02T14:34:29", 
    "device": "openaps://cgm", 
    "type": "sgv", 
    "glucose": 139
  }, 
  {
    "trend_arrow": "FLAT", 
    "system_time": "2016-08-02T22:30:00", 
    "direction": "Flat", 
    "sgv": 135, 
    "display_time": "2016-08-02T14:29:30", 
    "date": 1470162570000.0, 
    "dateString": "2016-08-02T14:29:30", 
    "device": "openaps://cgm", 
    "type": "sgv", 
    "glucose": 135
  }, 
  {
    "trend_arrow": "FLAT", 
    "system_time": "2016-08-02T22:25:00", 
    "direction": "Flat", 
    "sgv": 130, 
    "display_time": "2016-08-02T14:24:30", 
    "date": 1470162270000.0, 
    "dateString": "2016-08-02T14:24:30", 
    "device": "openaps://cgm", 
    "type": "sgv", 
    "glucose": 130
  }, 
  {
    "trend_arrow": "FLAT", 
    "system_time": "2016-08-02T22:20:07", 
    "direction": "Flat", 
    "sgv": 127, 
    "display_time": "2016-08-02T14:19:37", 
    "date": 1470161977000.0, 
    "dateString": "2016-08-02T14:19:37", 
    "device": "openaps://cgm", 
    "type": "sgv", 
    "glucose": 127
  }, 
  {
    "trend_arrow": "FLAT", 
    "system_time": "2016-08-02T22:15:00", 
    "direction": "Flat", 
    "sgv": 128, 
    "display_time": "2016-08-02T14:14:30", 
    "date": 1470161670000.0, 
    "dateString": "2016-08-02T14:14:30", 
    "device": "openaps://cgm", 
    "type": "sgv", 
    "glucose": 128
  }, 
  {
    "trend_arrow": "FLAT", 
    "system_time": "2016-08-02T22:05:03", 
    "direction": "Flat", 
    "sgv": 120, 
    "display_time": "2016-08-02T14:04:32", 
    "date": 1470161072000.0, 
    "dateString": "2016-08-02T14:04:32", 
    "device": "openaps://cgm", 
    "type": "sgv", 
    "glucose": 120
  }, 
  {
    "trend_arrow": "FLAT", 
    "system_time": "2016-08-02T22:00:00", 
    "direction": "Flat", 
    "sgv": 113, 
    "display_time": "2016-08-02T13:59:29", 
    "date": 1470160769000.0, 
    "dateString": "2016-08-02T13:59:29", 
    "device": "openaps://cgm", 
    "type": "sgv", 
    "glucose": 113
  }, 
  {
    "trend_arrow": "FLAT", 
    "system_time": "2016-08-02T21:55:01", 
    "direction": "Flat", 
    "sgv": 112, 
    "display_time": "2016-08-02T13:54:31", 
    "date": 1470160471000.0, 
    "dateString": "2016-08-02T13:54:31", 
    "device": "openaps://cgm", 
    "type": "sgv", 
    "glucose": 112
  }, 
  {
    "trend_arrow": "FLAT", 
    "system_time": "2016-08-02T21:50:02", 
    "direction": "Flat", 
    "sgv": 109, 
    "display_time": "2016-08-02T13:49:31", 
    "date": 1470160171000.0, 
    "dateString": "2016-08-02T13:49:31", 
    "device": "openaps://cgm", 
    "type": "sgv", 
    "glucose": 109
  }, 
  {
    "trend_arrow": "FLAT", 
    "system_time": "2016-08-02T21:45:01", 
    "direction": "Flat", 
    "sgv": 107, 
    "display_time": "2016-08-02T13:44:31", 
    "date": 1470159871000.0, 
    "dateString": "2016-08-02T13:44:31", 
    "device": "openaps://cgm", 
    "type": "sgv", 
    "glucose": 107
  }, 
  {
    "trend_arrow": "FLAT", 
    "system_time": "2016-08-02T21:40:00", 
    "direction": "Flat", 
    "sgv": 107, 
    "display_time": "2016-08-02T13:39:30", 
    "date": 1470159570000.0, 
    "dateString": "2016-08-02T13:39:30", 
    "device": "openaps://cgm", 
    "type": "sgv", 
    "glucose": 107
  }, 
  {
    "trend_arrow": "FLAT", 
    "system_time": "2016-08-02T21:35:01", 
    "direction": "Flat", 
    "sgv": 110, 
    "display_time": "2016-08-02T13:34:31", 
    "date": 1470159271000.0, 
    "dateString": "2016-08-02T13:34:31", 
    "device": "openaps://cgm", 
    "type": "sgv", 
    "glucose": 110
  }, 
  {
    "trend_arrow": "FLAT", 
    "system_time": "2016-08-02T21:30:01", 
    "direction": "Flat", 
    "sgv": 118, 
    "display_time": "2016-08-02T13:29:31", 
    "date": 1470158971000.0, 
    "dateString": "2016-08-02T13:29:31", 
    "device": "openaps://cgm", 
    "type": "sgv", 
    "glucose": 118
  }, 
  {
    "trend_arrow": "FLAT", 
    "system_time": "2016-08-02T21:25:08", 
    "direction": "Flat", 
    "sgv": 122, 
    "display_time": "2016-08-02T13:24:37", 
    "date": 1470158677000.0, 
    "dateString": "2016-08-02T13:24:37", 
    "device": "openaps://cgm", 
    "type": "sgv", 
    "glucose": 122
  }, 
  {
    "trend_arrow": "FLAT", 
    "system_time": "2016-08-02T21:20:03", 
    "direction": "Flat", 
    "sgv": 121, 
    "display_time": "2016-08-02T13:19:32", 
    "date": 1470158372000.0, 
    "dateString": "2016-08-02T13:19:32", 
    "device": "openaps://cgm", 
    "type": "sgv", 
    "glucose": 121
  }, 
  {
    "trend_arrow": "FLAT", 
    "system_time": "2016-08-02T21:15:04", 
    "direction": "Flat", 
    "sgv": 118, 
    "display_time": "2016-08-02T13:14:33", 
    "date": 1470158073000.0, 
    "dateString": "2016-08-02T13:14:33", 
    "device": "openaps://cgm", 
    "type": "sgv", 
    "glucose": 118
  }, 
  {
    "trend_arrow": "FLAT", 
    "system_time": "2016-08-02T21:10:02", 
    "direction": "Flat", 
    "sgv": 115, 
    "display_time": "2016-08-02T13:09:31", 
    "date": 1470157771000.0, 
    "dateString": "2016-08-02T13:09:31", 
    "device": "openaps://cgm", 
    "type": "sgv", 
    "glucose": 115
  }
]