[
  {
    "trend_arrow": "45_UP", 
    "display_time": "2016-08-03T04:34:28-04:00", 
    "direction": "FortyFiveUp", 
    "system_time": "2016-08-03T12:34:58", 
    "sgv": 124, 
    "dateString": "2016-08-03T04:34:28-04:00", 
    "device": "openaps://cgm", 
    "date": 1470213268000.0, 
    "type": "sgv", 
    "glucose": 124
  }, 
  {
    "trend_arrow": "45_UP", 
    "display_time": "2016-08-03T04:29:31-04:00", 
    "direction": "FortyFiveUp", 
    "system_time": "2016-08-03T12:30:02", 
    "sgv": 120, 
    "dateString": "2016-08-03T04:29:31-04:00", 
    "device": "openaps://cgm", 
    "date": 1470212971000.0, 
    "type": "sgv", 
    "glucose": 120
  }, 
  {
    "trend_arrow": "45_UP", 
    "display_time": "2016-08-03T04:24:28-04:00", 
    "direction": "FortyFiveUp", 
    "system_time": "2016-08-03T12:24:58", 
    "sgv": 116, 
    "dateString": "2016-08-03T04:24:28-04:00", 
    "device": "openaps://cgm", 
    "date": 1470212668000.0, 
    "type": "sgv", 
    "glucose": 116
  }, 
  {
    "trend_arrow": "FLAT", 
    "display_time": "2016-08-03T04:19:27-04:00", 
    "direction": "Flat", 
    "system_time": "2016-08-03T12:19:58", 
    "sgv": 110, 
    "dateString": "2016-08-03T04:19:27-04:00", 
    "device": "openaps://cgm", 
    "date": 1470212367000.0, 
    "type": "sgv", 
    "glucose": 110
  }, 
  {
    "trend_arrow": "FLAT", 
    "display_time": "2016-08-03T04:14:28-04:00", 
    "direction": "Flat", 
    "system_time": "2016-08-03T12:14:58", 
    "sgv": 102, 
    "dateString": "2016-08-03T04:14:28-04:00", 
    "device": "openaps://cgm", 
    "date": 1470212068000.0, 
    "type": "sgv", 
    "glucose": 102
  }, 
  {
    "trend_arrow": "FLAT", 
    "display_time": "2016-08-03T04:09:29-04:00", 
    "direction": "Flat", 
    "system_time": "2016-08-03T12:09:59", 
    "sgv": 101, 
    "dateString": "2016-08-03T04:09:29-04:00", 
    "device": "openaps://cgm", 
    "date": 1470211769000.0, 
    "type": "sgv", 
    "glucose": 101
  }, 
  {
    "trend_arrow": "FLAT", 
    "display_time": "2016-08-03T04:04:27-04:00", 
    "direction": "Flat", 
    "system_time": "2016-08-03T12:04:57", 
    "sgv": 98, 
    "dateString": "2016-08-03T04:04:27-04:00", 
    "device": "openaps://cgm", 
    "date": 1470211467000.0, 
    "type": "sgv", 
    "glucose": 98
  }, 
  {
    "trend_arrow": "FLAT", 
    "display_time": "2016-08-03T03:59:31-04:00", 
    "direction": "Flat", 
    "system_time": "2016-08-03T12:00:01", 
    "sgv": 95, 
    "dateString": "2016-08-03T03:59:31-04:00", 
    "device": "openaps://cgm", 
    "date": 1470211171000.0, 
    "type": "sgv", 
    "glucose": 95
  }, 
  {
    "trend_arrow": "FLAT", 
    "display_time": "2016-08-03T03:54:28-04:00", 
    "direction": "Flat", 
    "system_time": "2016-08-03T11:54:58", 
    "sgv": 91, 
    "dateString": "2016-08-03T03:54:28-04:00", 
    "device": "openaps://cgm", 
    "date": 1470210868000.0, 
    "type": "sgv", 
    "glucose": 91
  }, 
  {
    "trend_arrow": "FLAT", 
    "display_time": "2016-08-03T03:49:28-04:00", 
    "direction": "Flat", 
    "system_time": "2016-08-03T11:49:59", 
    "sgv": 86, 
    "dateString": "2016-08-03T03:49:28-04:00", 
    "device": "openaps://cgm", 
    "date": 1470210568000.0, 
    "type": "sgv", 
    "glucose": 86
  }, 
  {
    "trend_arrow": "FLAT", 
    "display_time": "2016-08-03T03:44:27-04:00", 
    "direction": "Flat", 
    "system_time": "2016-08-03T11:44:57", 
    "sgv": 85, 
    "dateString": "2016-08-03T03:44:27-04:00", 
    "device": "openaps://cgm", 
    "date": 1470210267000.0, 
    "type": "sgv", 
    "glucose": 85
  }, 
  {
    "trend_arrow": "FLAT", 
    "display_time": "2016-08-03T03:39:28-04:00", 
    "direction": "Flat", 
    "system_time": "2016-08-03T11:39:58", 
    "sgv": 86, 
    "dateString": "2016-08-03T03:39:28-04:00", 
    "device": "openaps://cgm", 
    "date": 1470209968000.0, 
    "type": "sgv", 
    "glucose": 86
  }, 
  {
    "trend_arrow": "FLAT", 
    "display_time": "2016-08-03T03:34:27-04:00", 
    "direction": "Flat", 
    "system_time": "2016-08-03T11:34:57", 
    "sgv": 88, 
    "dateString": "2016-08-03T03:34:27-04:00", 
    "device": "openaps://cgm", 
    "date": 1470209667000.0, 
    "type": "sgv", 
    "glucose": 88
  }, 
  {
    "trend_arrow": "45_DOWN", 
    "display_time": "2016-08-03T03:29:27-04:00", 
    "direction": "FortyFiveDown", 
    "system_time": "2016-08-03T11:29:57", 
    "sgv": 91, 
    "dateString": "2016-08-03T03:29:27-04:00", 
    "device": "openaps://cgm", 
    "date": 1470209367000.0, 
    "type": "sgv", 
    "glucose": 91
  }, 
  {
    "trend_arrow": "45_DOWN", 
    "display_time": "2016-08-03T03:24:27-04:00", 
    "direction": "FortyFiveDown", 
    "system_time": "2016-08-03T11:24:58", 
    "sgv": 94, 
    "dateString": "2016-08-03T03:24:27-04:00", 
    "device": "openaps://cgm", 
    "date": 1470209067000.0, 
    "type": "sgv", 
    "glucose": 94
  }, 
  {
    "trend_arrow": "45_DOWN", 
    "display_time": "2016-08-03T03:19:27-04:00", 
    "direction": "FortyFiveDown", 
    "system_time": "2016-08-03T11:19:58", 
    "sgv": 99, 
    "dateString": "2016-08-03T03:19:27-04:00", 
    "device": "openaps://cgm", 
    "date": 1470208767000.0, 
    "type": "sgv", 
    "glucose": 99
  }, 
  {
    "trend_arrow": "45_DOWN", 
    "display_time": "2016-08-03T03:14:36-04:00", 
    "direction": "FortyFiveDown", 
    "system_time": "2016-08-03T11:15:07", 
    "sgv": 106, 
    "dateString": "2016-08-03T03:14:36-04:00", 
    "device": "openaps://cgm", 
    "date": 1470208476000.0, 
    "type": "sgv", 
    "glucose": 106
  }, 
  {
    "trend_arrow": "45_DOWN", 
    "display_time": "2016-08-03T03:09:28-04:00", 
    "direction": "FortyFiveDown", 
    "system_time": "2016-08-03T11:09:58", 
    "sgv": 112, 
    "dateString": "2016-08-03T03:09:28-04:00", 
    "device": "openaps://cgm", 
    "date": 1470208168000.0, 
    "type": "sgv", 
    "glucose": 112
  }, 
  {
    "trend_arrow": "45_DOWN", 
    "display_time": "2016-08-03T03:04:29-04:00", 
    "direction": "FortyFiveDown", 
    "system_time": "2016-08-03T11:05:00", 
    "sgv": 118, 
    "dateString": "2016-08-03T03:04:29-04:00", 
    "device": "openaps://cgm", 
    "date": 1470207869000.0, 
    "type": "sgv", 
    "glucose": 118
  }, 
  {
    "trend_arrow": "45_DOWN", 
    "display_time": "2016-08-03T02:59:32-04:00", 
    "direction": "FortyFiveDown", 
    "system_time": "2016-08-03T11:00:02", 
    "sgv": 123, 
    "dateString": "2016-08-03T02:59:32-04:00", 
    "device": "openaps://cgm", 
    "date": 1470207572000.0, 
    "type": "sgv", 
    "glucose": 123
  }, 
  {
    "trend_arrow": "45_DOWN", 
    "display_time": "2016-08-03T02:54:31-04:00", 
    "direction": "FortyFiveDown", 
    "system_time": "2016-08-03T10:55:02", 
    "sgv": 130, 
    "dateString": "2016-08-03T02:54:31-04:00", 
    "device": "openaps://cgm", 
    "date": 1470207271000.0, 
    "type": "sgv", 
    "glucose": 130
  }, 
  {
    "trend_arrow": "45_DOWN", 
    "display_time": "2016-08-03T02:49:28-04:00", 
    "direction": "FortyFiveDown", 
    "system_time": "2016-08-03T10:49:58", 
    "sgv": 135, 
    "dateString": "2016-08-03T02:49:28-04:00", 
    "device": "openaps://cgm", 
    "date": 1470206968000.0, 
    "type": "sgv", 
    "glucose": 135
  }, 
  {
    "trend_arrow": "45_DOWN", 
    "display_time": "2016-08-03T02:44:33-04:00", 
    "direction": "FortyFiveDown", 
    "system_time": "2016-08-03T10:45:04", 
    "sgv": 141, 
    "dateString": "2016-08-03T02:44:33-04:00", 
    "device": "openaps://cgm", 
    "date": 1470206673000.0, 
    "type": "sgv", 
    "glucose": 141
  }, 
  {
    "trend_arrow": "45_DOWN", 
    "display_time": "2016-08-03T02:39:32-04:00", 
    "direction": "FortyFiveDown", 
    "system_time": "2016-08-03T10:40:02", 
    "sgv": 148, 
    "dateString": "2016-08-03T02:39:32-04:00", 
    "device": "openaps://cgm", 
    "date": 1470206372000.0, 
    "type": "sgv", 
    "glucose": 148
  }
]