[
  {
    "trend_arrow": "FLAT", 
    "display_time": "2016-07-18T15:55:22-04:00", 
    "direction": "Flat", 
    "system_time": "2016-07-18T23:55:22", 
    "sgv": 106, 
    "dateString": "2016-07-18T15:55:22-04:00", 
    "device": "openaps://cgm", 
    "date": 1468871722000.0, 
    "type": "sgv", 
    "glucose": 106
  }, 
  {
    "trend_arrow": "FLAT", 
    "display_time": "2016-07-18T15:50:22-04:00", 
    "direction": "Flat", 
    "system_time": "2016-07-18T23:50:22", 
    "sgv": 103, 
    "dateString": "2016-07-18T15:50:22-04:00", 
    "device": "openaps://cgm", 
    "date": 1468871422000.0, 
    "type": "sgv", 
    "glucose": 103
  }, 
  {
    "trend_arrow": "FLAT", 
    "display_time": "2016-07-18T15:45:22-04:00", 
    "direction": "Flat", 
    "system_time": "2016-07-18T23:45:23", 
    "sgv": 100, 
    "dateString": "2016-07-18T15:45:22-04:00", 
    "device": "openaps://cgm", 
    "date": 1468871122000.0, 
    "type": "sgv", 
    "glucose": 100
  }, 
  {
    "trend_arrow": "FLAT", 
    "display_time": "2016-07-18T15:40:23-04:00", 
    "direction": "Flat", 
    "system_time": "2016-07-18T23:40:23", 
    "sgv": 99, 
    "dateString": "2016-07-18T15:40:23-04:00", 
    "device": "openaps://cgm", 
    "date": 1468870823000.0, 
    "type": "sgv", 
    "glucose": 99
  }, 
  {
    "trend_arrow": "FLAT", 
    "display_time": "2016-07-18T15:35:20-04:00", 
    "direction": "Flat", 
    "system_time": "2016-07-18T23:35:21", 
    "sgv": 103, 
    "dateString": "2016-07-18T15:35:20-04:00", 
    "device": "openaps://cgm", 
    "date": 1468870520000.0, 
    "type": "sgv", 
    "glucose": 103
  }, 
  {
    "trend_arrow": "FLAT", 
    "display_time": "2016-07-18T15:30:20-04:00", 
    "direction": "Flat", 
    "system_time": "2016-07-18T23:30:21", 
    "sgv": 104, 
    "dateString": "2016-07-18T15:30:20-04:00", 
    "device": "openaps://cgm", 
    "date": 1468870220000.0, 
    "type": "sgv", 
    "glucose": 104
  }, 
  {
    "trend_arrow": "FLAT", 
    "display_time": "2016-07-18T15:25:20-04:00", 
    "direction": "Flat", 
    "system_time": "2016-07-18T23:25:21", 
    "sgv": 102, 
    "dateString": "2016-07-18T15:25:20-04:00", 
    "device": "openaps://cgm", 
    "date": 1468869920000.0, 
    "type": "sgv", 
    "glucose": 102
  }, 
  {
    "trend_arrow": "FLAT", 
    "display_time": "2016-07-18T15:20:20-04:00", 
    "direction": "Flat", 
    "system_time": "2016-07-18T23:20:21", 
    "sgv": 101, 
    "dateString": "2016-07-18T15:20:20-04:00", 
    "device": "openaps://cgm", 
    "date": 1468869620000.0, 
    "type": "sgv", 
    "glucose": 101
  }, 
  {
    "trend_arrow": "FLAT", 
    "display_time": "2016-07-18T15:15:20-04:00", 
    "direction": "Flat", 
    "system_time": "2016-07-18T23:15:21", 
    "sgv": 97, 
    "dateString": "2016-07-18T15:15:20-04:00", 
    "device": "openaps://cgm", 
    "date": 1468869320000.0, 
    "type": "sgv", 
    "glucose": 97
  }, 
  {
    "trend_arrow": "FLAT", 
    "display_time": "2016-07-18T15:10:20-04:00", 
    "direction": "Flat", 
    "system_time": "2016-07-18T23:10:21", 
    "sgv": 98, 
    "dateString": "2016-07-18T15:10:20-04:00", 
    "device": "openaps://cgm", 
    "date": 1468869020000.0, 
    "type": "sgv", 
    "glucose": 98
  }, 
  {
    "trend_arrow": "FLAT", 
    "display_time": "2016-07-18T15:05:40-04:00", 
    "direction": "Flat", 
    "system_time": "2016-07-18T23:05:41", 
    "sgv": 98, 
    "dateString": "2016-07-18T15:05:40-04:00", 
    "device": "openaps://cgm", 
    "date": 1468868740000.0, 
    "type": "sgv", 
    "glucose": 98
  }, 
  {
    "trend_arrow": "FLAT", 
    "display_time": "2016-07-18T15:00:40-04:00", 
    "direction": "Flat", 
    "system_time": "2016-07-18T23:00:41", 
    "sgv": 100, 
    "dateString": "2016-07-18T15:00:40-04:00", 
    "device": "openaps://cgm", 
    "date": 1468868440000.0, 
    "type": "sgv", 
    "glucose": 100
  }, 
  {
    "trend_arrow": "FLAT", 
    "display_time": "2016-07-18T14:55:23-04:00", 
    "direction": "Flat", 
    "system_time": "2016-07-18T22:55:23", 
    "sgv": 99, 
    "dateString": "2016-07-18T14:55:23-04:00", 
    "device": "openaps://cgm", 
    "date": 1468868123000.0, 
    "type": "sgv", 
    "glucose": 99
  }, 
  {
    "trend_arrow": "FLAT", 
    "display_time": "2016-07-18T14:50:27-04:00", 
    "direction": "Flat", 
    "system_time": "2016-07-18T22:50:27", 
    "sgv": 102, 
    "dateString": "2016-07-18T14:50:27-04:00", 
    "device": "openaps://cgm", 
    "date": 1468867827000.0, 
    "type": "sgv", 
    "glucose": 102
  }, 
  {
    "trend_arrow": "FLAT", 
    "display_time": "2016-07-18T14:45:21-04:00", 
    "direction": "Flat", 
    "system_time": "2016-07-18T22:45:22", 
    "sgv": 101, 
    "dateString": "2016-07-18T14:45:21-04:00", 
    "device": "openaps://cgm", 
    "date": 1468867521000.0, 
    "type": "sgv", 
    "glucose": 101
  }, 
  {
    "trend_arrow": "FLAT", 
    "display_time": "2016-07-18T14:40:23-04:00", 
    "direction": "Flat", 
    "system_time": "2016-07-18T22:40:24", 
    "sgv": 101, 
    "dateString": "2016-07-18T14:40:23-04:00", 
    "device": "openaps://cgm", 
    "date": 1468867223000.0, 
    "type": "sgv", 
    "glucose": 101
  }, 
  {
    "trend_arrow": "FLAT", 
    "display_time": "2016-07-18T14:35:24-04:00", 
    "direction": "Flat", 
    "system_time": "2016-07-18T22:35:24", 
    "sgv": 101, 
    "dateString": "2016-07-18T14:35:24-04:00", 
    "device": "openaps://cgm", 
    "date": 1468866924000.0, 
    "type": "sgv", 
    "glucose": 101
  }, 
  {
    "trend_arrow": "FLAT", 
    "display_time": "2016-07-18T14:30:22-04:00", 
    "direction": "Flat", 
    "system_time": "2016-07-18T22:30:22", 
    "sgv": 101, 
    "dateString": "2016-07-18T14:30:22-04:00", 
    "device": "openaps://cgm", 
    "date": 1468866622000.0, 
    "type": "sgv", 
    "glucose": 101
  }, 
  {
    "trend_arrow": "FLAT", 
    "display_time": "2016-07-18T14:25:21-04:00", 
    "direction": "Flat", 
    "system_time": "2016-07-18T22:25:22", 
    "sgv": 102, 
    "dateString": "2016-07-18T14:25:21-04:00", 
    "device": "openaps://cgm", 
    "date": 1468866321000.0, 
    "type": "sgv", 
    "glucose": 102
  }, 
  {
    "trend_arrow": "FLAT", 
    "display_time": "2016-07-18T14:20:24-04:00", 
    "direction": "Flat", 
    "system_time": "2016-07-18T22:20:24", 
    "sgv": 102, 
    "dateString": "2016-07-18T14:20:24-04:00", 
    "device": "openaps://cgm", 
    "date": 1468866024000.0, 
    "type": "sgv", 
    "glucose": 102
  }, 
  {
    "trend_arrow": "FLAT", 
    "display_time": "2016-07-18T14:15:24-04:00", 
    "direction": "Flat", 
    "system_time": "2016-07-18T22:15:25", 
    "sgv": 116, 
    "dateString": "2016-07-18T14:15:24-04:00", 
    "device": "openaps://cgm", 
    "date": 1468865724000.0, 
    "type": "sgv", 
    "glucose": 116
  }, 
  {
    "trend_arrow": "FLAT", 
    "display_time": "2016-07-18T14:10:22-04:00", 
    "direction": "Flat", 
    "system_time": "2016-07-18T22:10:23", 
    "sgv": 117, 
    "dateString": "2016-07-18T14:10:22-04:00", 
    "device": "openaps://cgm", 
    "date": 1468865422000.0, 
    "type": "sgv", 
    "glucose": 117
  }, 
  {
    "trend_arrow": "FLAT", 
    "display_time": "2016-07-18T14:05:22-04:00", 
    "direction": "Flat", 
    "system_time": "2016-07-18T22:05:23", 
    "sgv": 118, 
    "dateString": "2016-07-18T14:05:22-04:00", 
    "device": "openaps://cgm", 
    "date": 1468865122000.0, 
    "type": "sgv", 
    "glucose": 118
  }, 
  {
    "trend_arrow": "FLAT", 
    "display_time": "2016-07-18T14:00:36-04:00", 
    "direction": "Flat", 
    "system_time": "2016-07-18T22:00:36", 
    "sgv": 120, 
    "dateString": "2016-07-18T14:00:36-04:00", 
    "device": "openaps://cgm", 
    "date": 1468864836000.0, 
    "type": "sgv", 
    "glucose": 120
  }
]