[
  {
    "i": 0, 
    "start": "00:00:00", 
    "rate": 0.7250000000000001, 
    "minutes": 0
  }, 
  {
    "i": 1, 
    "start": "05:00:00", 
    "rate": 0.7000000000000001, 
    "minutes": 300
  }, 
  {
    "i": 2, 
    "start": "07:00:00", 
    "rate": 0.9500000000000001, 
    "minutes": 420
  }, 
  {
    "i": 3, 
    "start": "11:00:00", 
    "rate": 0.7000000000000001, 
    "minutes": 660
  }, 
  {
    "i": 4, 
    "start": "14:00:00", 
    "rate": 0.8500000000000001, 
    "minutes": 840
  }, 
  {
    "i": 5, 
    "start": "16:00:00", 
    "rate": 0.7000000000000001, 
    "minutes": 960
  }
]